pyp3rclip/__init__.py
pyp3rclip/__main__.py
pyp3rclip-1.8.0.dist-info/AUTHORS.txt
pyp3rclip-1.8.0.dist-info/LICENSE.txt
pyp3rclip-1.8.0.dist-info/METADATA
pyp3rclip-1.8.0.dist-info/WHEEL
pyp3rclip-1.8.0.dist-info/top_level.txt
pyp3rclip-1.8.0.dist-info/RECORD
